finance_scrapers/__init__.py
finance_scrapers/downloader.py
finance_scrapers/yahoo_finance.py
finance_scrapers-2.0.0.dist-info/LICENSE
finance_scrapers-2.0.0.dist-info/METADATA
finance_scrapers-2.0.0.dist-info/WHEEL
finance_scrapers-2.0.0.dist-info/top_level.txt
finance_scrapers-2.0.0.dist-info/RECORD
