Metadata-Version: 2.1
Name: finance-scrapers
Version: 2.0.0
Summary: A tool to scrape and download publicly available stock information. Currently supports Yahoo Finance data.
Home-page: https://github.com/Mandy-cyber/Yahoo-Finance
Author: Mandy-cyber
Keywords: python,bs4,stocks,requests,stock-data,yahoofinance,finance
Classifier: Programming Language :: Python :: 3
Classifier: License :: OSI Approved :: MIT License
Classifier: Operating System :: OS Independent
Requires-Python: >=3.6
License-File: LICENSE
Requires-Dist: requests
Requires-Dist: bs4
Requires-Dist: html5lib
Requires-Dist: pandas
Requires-Dist: openpyxl
